{"name":null,"assets":"aoy4:sizei341324y4:typey4:FONTy9:classNamey28:__ASSET__assets_ubuntu_m_ttfy2:idy21:assets%2FUbuntu-M.ttfy7:preloadtgoy4:pathy17:assets%2Flogo.pngR0i12147R1y5:IMAGER5R9R7tgoR0i39706R1y5:MUSICR5y28:flixel%2Fsounds%2Fflixel.mp3y9:pathGroupaR12y28:flixel%2Fsounds%2Fflixel.ogghR7tgoR0i8220R1R11R5y26:flixel%2Fsounds%2Fbeep.mp3R13aR15y26:flixel%2Fsounds%2Fbeep.ogghR7tgoR0i33629R1y5:SOUNDR5R14R13aR12R14hgoR0i6840R1R17R5R16R13aR15R16hgoR0i15744R1R2R3y35:__ASSET__flixel_fonts_nokiafc22_ttfR5y30:flixel%2Ffonts%2Fnokiafc22.ttfR7tgoR0i29724R1R2R3y36:__ASSET__flixel_fonts_monsterrat_ttfR5y31:flixel%2Ffonts%2Fmonsterrat.ttfR7tgoR8y33:flixel%2Fimages%2Fui%2Fbutton.pngR0i222R1R10R5R22R7tgoR8y36:flixel%2Fimages%2Flogo%2Fdefault.pngR0i484R1R10R5R23R7tgoR8y42:flixel%2Fimages%2Ftransitions%2Fsquare.pngR0i209R1R10R5R24R7tgoR8y42:flixel%2Fimages%2Ftransitions%2Fcircle.pngR0i299R1R10R5R25R7tgoR8y43:flixel%2Fimages%2Ftransitions%2Fdiamond.pngR0i236R1R10R5R26R7tgoR8y53:flixel%2Fimages%2Ftransitions%2Fdiagonal_gradient.pngR0i730R1R10R5R27R7tgh","rootPath":null,"version":2,"libraryArgs":[],"libraryType":null}